cython_naive/_compute.cp310-win32.pyd
mandelbrot_implementations_cython_naive-0.1.0.dist-info/METADATA
mandelbrot_implementations_cython_naive-0.1.0.dist-info/WHEEL
mandelbrot_implementations_cython_naive-0.1.0.dist-info/top_level.txt
mandelbrot_implementations_cython_naive-0.1.0.dist-info/RECORD
